ipyniivue/__init__.py
ipyniivue/config_options.py
ipyniivue/constants.py
ipyniivue/download_dataset.py
ipyniivue/serializers.py
ipyniivue/traits.py
ipyniivue/utils.py
ipyniivue/widget.py
ipyniivue/static/meshShaderNames.txt
ipyniivue/static/widget.js
ipyniivue/static/colormaps/$itksnap.json
ipyniivue/static/colormaps/$slicer3d.json
ipyniivue/static/colormaps/actc.json
ipyniivue/static/colormaps/afni_blues_inv.json
ipyniivue/static/colormaps/afni_reds_inv.json
ipyniivue/static/colormaps/batlow.json
ipyniivue/static/colormaps/bcgwhw.json
ipyniivue/static/colormaps/bcgwhw_dark.json
ipyniivue/static/colormaps/blue.json
ipyniivue/static/colormaps/blue2cyan.json
ipyniivue/static/colormaps/blue2magenta.json
ipyniivue/static/colormaps/blue2red.json
ipyniivue/static/colormaps/bluegrn.json
ipyniivue/static/colormaps/bone.json
ipyniivue/static/colormaps/bronze.json
ipyniivue/static/colormaps/cet_l17.json
ipyniivue/static/colormaps/cividis.json
ipyniivue/static/colormaps/cool.json
ipyniivue/static/colormaps/copper.json
ipyniivue/static/colormaps/copper2.json
ipyniivue/static/colormaps/ct_airways.json
ipyniivue/static/colormaps/ct_artery.json
ipyniivue/static/colormaps/ct_bones.json
ipyniivue/static/colormaps/ct_brain.json
ipyniivue/static/colormaps/ct_brain_gray.json
ipyniivue/static/colormaps/ct_cardiac.json
ipyniivue/static/colormaps/ct_head.json
ipyniivue/static/colormaps/ct_kidneys.json
ipyniivue/static/colormaps/ct_liver.json
ipyniivue/static/colormaps/ct_muscles.json
ipyniivue/static/colormaps/ct_scalp.json
ipyniivue/static/colormaps/ct_skull.json
ipyniivue/static/colormaps/ct_soft.json
ipyniivue/static/colormaps/ct_soft_tissue.json
ipyniivue/static/colormaps/ct_surface.json
ipyniivue/static/colormaps/ct_vessels.json
ipyniivue/static/colormaps/ct_w_contrast.json
ipyniivue/static/colormaps/cubehelix.json
ipyniivue/static/colormaps/electric_blue.json
ipyniivue/static/colormaps/freesurfer.json
ipyniivue/static/colormaps/ge_color.json
ipyniivue/static/colormaps/gold.json
ipyniivue-2.4.4.dist-info/METADATA
ipyniivue-2.4.4.dist-info/WHEEL
ipyniivue-2.4.4.dist-info/licenses/LICENSE
ipyniivue-2.4.4.dist-info/RECORD
