Metadata-Version: 2.4
Name: ipyniivue
Version: 2.4.4
Summary: A Jupyter Widget for Niivue based on anywidget.
Project-URL: homepage, https://github.com/niivue/ipyniivue
License: BSD-2-Clause
License-File: LICENSE
Classifier: Framework :: Jupyter
Classifier: Framework :: Jupyter :: JupyterLab
Classifier: Framework :: Jupyter :: JupyterLab :: 4
Classifier: Framework :: Jupyter :: JupyterLab :: Extensions
Classifier: Framework :: Jupyter :: JupyterLab :: Extensions :: Prebuilt
Classifier: License :: OSI Approved :: BSD License
Classifier: Programming Language :: Python
Classifier: Programming Language :: Python :: 3
Requires-Python: >=3.9
Requires-Dist: anywidget
Requires-Dist: numpy>=2.0.2
Requires-Dist: requests
Provides-Extra: dev
Requires-Dist: furo; extra == 'dev'
Requires-Dist: jupyterlab; extra == 'dev'
Requires-Dist: myst-parser; extra == 'dev'
Requires-Dist: pytest; extra == 'dev'
Requires-Dist: ruff; extra == 'dev'
Requires-Dist: sphinx; extra == 'dev'
Requires-Dist: sphinxcontrib-mermaid; extra == 'dev'
Requires-Dist: watchfiles; extra == 'dev'
